{"cameraMode":{"drawMode":0,"name":"Shaded","section":"Shading Mode"},"sceneLighting":true,"audioPlay":false,"sceneViewState":{"m_AlwaysRefresh":false,"showFog":true,"showSkybox":true,"showFlares":true,"showImageEffects":true,"showParticleSystems":true,"showVisualEffectGraphs":true,"m_FxEnabled":true},"in2DMode":false,"pivot":{"x":-10.285415649414063,"y":9.0524320602417,"z":66.31737518310547},"rotation":{"x":-0.02152021788060665,"y":0.9739250540733337,"z":-0.10410024970769882,"w":-0.2005424201488495},"size":2.3277945518493654,"orthographic":false}